friendly_custom_exception/__init__.py
friendly_custom_exception-0.0.1.dist-info/LICENSE
friendly_custom_exception-0.0.1.dist-info/METADATA
friendly_custom_exception-0.0.1.dist-info/WHEEL
friendly_custom_exception-0.0.1.dist-info/top_level.txt
friendly_custom_exception-0.0.1.dist-info/RECORD
