Metadata-Version: 2.1
Name: friendly-custom-exception
Version: 0.0.1
Summary: Showing how to add custom exceptions to friendly-traceback
Home-page: https://github.com/friendly-traceback/friendly-custom-exception
Author: Andre Roberge
Author-email: Andre.Roberge@gmail.com
Classifier: Development Status :: 1 - Planning
Classifier: Environment :: Console
Classifier: License :: OSI Approved :: MIT License
Classifier: Natural Language :: English
Classifier: Programming Language :: Python :: 3
Classifier: Programming Language :: Python :: 3.8
Classifier: Programming Language :: Python :: 3.9
Classifier: Programming Language :: Python :: 3.10
Classifier: Intended Audience :: Education
Classifier: Topic :: Education
Requires-Python: >=3.8
License-File: LICENSE
Requires-Dist: friendly (>=0.5.35)
Requires-Dist: jupyter
